pynfsesp/.DS_Store
pynfsesp/__init__.py
pynfsesp/gateways/__init__.py
pynfsesp/gateways/saopaulo.py
pynfsesp/utils/__init__.py
pynfsesp/utils/certificate.py
pynfsesp/utils/compatibility.py
pynfsesp/utils/currency.py
pynfsesp/utils/response.py
pynfsesp/utils/rps.py
pynfsesp/utils/rsa.py
pynfsesp/utils/schemas.py
pynfsesp-0.1.0.dist-info/WHEEL
pynfsesp-0.1.0.dist-info/METADATA
pynfsesp-0.1.0.dist-info/RECORD
