Metadata-Version: 2.1
Name: pynfsesp
Version: 0.1.0
Summary: Módulo para emissão de Notas Fiscais de Serviço para a Prefeitura de SP
License: MIT
Author: Bruno Souza
Author-email: bruno@komu.com.br
Requires-Python: >=3.8,<4.0
Classifier: License :: OSI Approved :: MIT License
Classifier: Programming Language :: Python :: 3
Classifier: Programming Language :: Python :: 3.10
Classifier: Programming Language :: Python :: 3.8
Classifier: Programming Language :: Python :: 3.9
Requires-Dist: lxml (>=4.8.0,<5.0.0)
Requires-Dist: pycrypto (>=2.6.1,<3.0.0)
Requires-Dist: requests (>=2.27.1,<3.0.0)
Requires-Dist: rsa (>=4.8,<5.0)
Requires-Dist: urllib3 (>=1.26.8,<2.0.0)
